intergalactic_namerator/__init__.py
intergalactic_namerator/main.py
intergalactic_namerator/models.py
intergalactic_namerator/utils.py
intergalactic_namerator-0.1.4.dist-info/METADATA
intergalactic_namerator-0.1.4.dist-info/WHEEL
intergalactic_namerator-0.1.4.dist-info/RECORD
