Metadata-Version: 2.4
Name: intergalactic-namerator
Version: 0.1.4
Summary: Generate names based on Rick and Morty characters.
Author-email: Koen van Esterik <kd.vanesterik@student.han.nl>
Requires-Python: >=3.12
Requires-Dist: bs4>=0.0.2
Requires-Dist: loguru>=0.7.3
Requires-Dist: pydantic>=2.12.4
Requires-Dist: requests>=2.32.5
Requires-Dist: tokenizers>=0.22.1
